LICENSE
MANIFEST.in
README.md
setup.py
pyrssa/__init__.py
pyrssa/base.py
pyrssa/conversion.py
pyrssa/docs.py
pyrssa/indexing.py
pyrssa/installer.py
pyrssa/plot.py
pyrssa.egg-info/PKG-INFO
pyrssa.egg-info/SOURCES.txt
pyrssa.egg-info/dependency_links.txt
pyrssa.egg-info/requires.txt
pyrssa.egg-info/top_level.txt
pyrssa/classes/AutoSSA.py
pyrssa/classes/Cadzow.py
pyrssa/classes/Forecast.py
pyrssa/classes/Gapfill.py
pyrssa/classes/HMatrix.py
pyrssa/classes/LRR.py
pyrssa/classes/Parestimate.py
pyrssa/classes/Periodogram.py
pyrssa/classes/Resonstruction.py
pyrssa/classes/SSA.py
pyrssa/classes/WCorMatrix.py
pyrssa/classes/__init__.py
pyrssa/data/AustralianWine.csv
pyrssa/data/Barbara.csv
pyrssa/data/Mars.csv
pyrssa/data/MotorVehicle.csv
pyrssa/data/USUnemployment.csv
pyrssa/data/bookings.csv
pyrssa/data/brecon.csv
pyrssa/data/cadzow.sim.csv
pyrssa/data/co2.csv
pyrssa/data/cowtemp.csv
pyrssa/data/dftreering.csv
pyrssa/data/dwarfst.csv
pyrssa/data/elec.csv
pyrssa/data/g15.csv
pyrssa/data/hotel.csv
pyrssa/data/iossa.err.csv
pyrssa/data/kruppel.csv
pyrssa/data/monet.csv
pyrssa/data/oilproduction.csv
pyrssa/data/paynsa.csv
pyrssa/data/sunspot2.csv
pyrssa/data/toeplitz.sim.csv
pyrssa/extdoc/calc_v.rst
pyrssa/extdoc/parestimate.rst
pyrssa/extdoc/ssa.rst
tests/test_ssa_1d.py
tests/tests_methods.py