Metadata-Version: 2.1
Name: pyrssa
Version: 1.0.11
Summary: Rssa for Python
Home-page: https://github.com/Fleyderer/pyrssa
Author: Fleyderer
Author-email: fleyderer@gmail.com
License: Apache 2.0
License-File: LICENSE
